contrib/__init__.py
contrib/normalizers/__init__.py
contrib/normalizers/acrux1.py
contrib/normalizers/common.py
contrib/normalizers/dummy.py
contrib/normalizers/lightsail2.py
contrib/normalizers/space_weather.py
polaris/__init__.py
polaris/_version.py
polaris/polaris.py
polaris/anomaly/__init__.py
polaris/anomaly/anomaly_detector_parameters.py
polaris/anomaly/detector.py
polaris/batch/__init__.py
polaris/batch/batch.py
polaris/common/__init__.py
polaris/common/config.py
polaris/common/constants.py
polaris/common/json_serializable.py
polaris/common/learn_parameters.py
polaris/common/util.py
polaris/convert/__init__.py
polaris/convert/gexf.py
polaris/convert/graph_converter.py
polaris/data/__init__.py
polaris/data/fetched_data_preprocessor.py
polaris/data/graph.py
polaris/data/readers.py
polaris/dataset/__init__.py
polaris/dataset/dataset.py
polaris/dataset/frame.py
polaris/dataset/metadata.py
polaris/feature/__init__.py
polaris/feature/cleaner.py
polaris/feature/cleaner_configurator.py
polaris/feature/cleaner_parameters.py
polaris/fetch/__init__.py
polaris/fetch/data_fetch_decoder.py
polaris/fetch/fetch_import_sw.py
polaris/fetch/fetch_import_telemetry.py
polaris/fetch/list_satellites.py
polaris/fetch/satellites.json
polaris/learn/__init__.py
polaris/learn/analysis.py
polaris/learn/feature/__init__.py
polaris/learn/feature/extraction.py
polaris/learn/feature/selection.py
polaris/learn/miner/__init__.py
polaris/learn/predictor/__init__.py
polaris/learn/predictor/cross_correlation.py
polaris/learn/predictor/cross_correlation_configurator.py
polaris/learn/predictor/cross_correlation_parameters.py
polaris/viz/__init__.py
polaris/viz/dynamic_network_analysis_3d-ui.html
polaris/viz/favicon.ico
polaris/viz/modal.css
polaris/viz/polaris.js
polaris/viz/server.py
polaris/viz/style_sheet.css
polaris/viz/toast.css
tests/__init__.py
tests/conftest.py
tests/test_anomaly_detector_parameters.py
tests/test_batch.py
tests/test_cleaner_configurator.py
tests/test_configuration.py
polaris_ml-0.13.5.dist-info/LICENSE
polaris_ml-0.13.5.dist-info/METADATA
polaris_ml-0.13.5.dist-info/WHEEL
polaris_ml-0.13.5.dist-info/entry_points.txt
polaris_ml-0.13.5.dist-info/top_level.txt
polaris_ml-0.13.5.dist-info/RECORD
