Metadata-Version: 2.1
Name: polaris-ml
Version: 0.13.5
Summary: Polaris
Home-page: https://gitlab.com/librespacefoundation/polaris/polaris
Author: 
Author-email: 
License: LGPLv3
Keywords: telemetry, satellite, machine learning
Platform: UNKNOWN
Classifier: Development Status :: 3 - Alpha
Classifier: Intended Audience :: Developers
Classifier: License :: OSI Approved :: GNU Lesser General Public License v3 (LGPLv3)
Classifier: Programming Language :: Python :: 3
Requires-Python: >=3
License-File: LICENSE
Requires-Dist: numpy
Requires-Dist: kaitaistruct
Requires-Dist: glouton (==0.11.1)
Requires-Dist: click
Requires-Dist: tqdm
Requires-Dist: pandas
Requires-Dist: scikit-learn (>0.23.0)
Requires-Dist: xgboost
Requires-Dist: satnogs-decoders
Requires-Dist: fets
Requires-Dist: mlflow
Requires-Dist: mergedeep
Requires-Dist: GPUtil (==1.4.0)
Requires-Dist: vinvelivaanilai (>=1.0.6)
Requires-Dist: enlighten
Requires-Dist: betsi-ml (>=0.0.3)
Provides-Extra: docs
Requires-Dist: myst-parser ; extra == 'docs'
Requires-Dist: sphinx ; extra == 'docs'
